{
  "pages": [
    {
      "id": "Page1",
      "isDefault": true
    },
    {
      "id": "Page2",
      "isDefault": false
    }
  ],
  "viewMode": false,
  "appIsExample": false,
  "unreadCommentThreads": 0,
  "clonedFromApplicationId": "651bf15db2195c63088dc6cd",
  "color": "#E3DEFF",
  "unpublishedCustomJSLibs": [],
  "publishedCustomJSLibs": [],
  "evaluationVersion": 2,
  "applicationVersion": 2,
  "embedSetting": {
    "height": "720px",
    "width": "1024px",
    "showNavigationBar": true
  },
  "collapseInvisibleWidgets": true,
  "isManualUpdate": false,
  "deleted": false
}